{
  "$schema": "_schema.json",
  "id": 209,
  "title": "The Umbrella Academy",
  "type": "SERIES",
  "style": "LIVE_ACTION",
  "releaseDate": "2019-02-15T00:00:00.000Z",
  "duration": 60,
  "poster": "posters/umbrella_academy.webp",
  "rating": 2,
  "description": "<p><b>Season 1</b>. On the same day in October 1989, forty-three infants are inexplicably born to random, unconnected women who showed no signs of pregnancy the day before. Seven are adopted by Sir Reginald Hargreeves, who creates The Umbrella Academy and prepares his \"children\" to save the world. But not everything went according to plan. In their teenage years, the family fractured and the team disbanded. Now almost thirty years old, the six surviving members reunite upon the news of Hargreeves' passing. Luther, Diego, Allison, Klaus, Vanya and Number Five work together to solve a mystery surrounding their father's death. But the estranged family once again begins to come apart due to their divergent personalities and abilities, not to mention the imminent threat of a global apocalypse.</p><p><b>Season 2</b>. The second season sees the siblings time-travel to the 1960s, where they must once again prevent a doomsday event. Each sibling faces new challenges and adventures in a different era, all while trying to reunite and make sense of the temporal chaos they find themselves in.</p><p><b>Season 3</b>. Back at the Academy, the Umbrellas clash with a new squad of Hargreeves siblings as a mysterious force begins to wreak havoc on the city.</p>",
  "chapterKey": null,
  "chapterOrder": null,
  "awards": [],
  "cast": [
    {
      "personId": 1134,
      "characterName": "Luther Hargreeves",
      "characterImage": null
    },
    {
      "personId": 268,
      "characterName": "Diego Hargreeves",
      "characterImage": null
    },
    {
      "personId": 348,
      "characterName": "Allison Hargreeves",
      "characterImage": null
    },
    {
      "personId": 992,
      "characterName": "Klaus Hargreeves",
      "characterImage": null
    },
    {
      "personId": 17,
      "characterName": "Number Five",
      "characterImage": null
    },
    {
      "personId": 632,
      "characterName": "Ben Hargreeves",
      "characterImage": null
    },
    {
      "personId": 334,
      "characterName": "Vanya Hargreeves",
      "characterImage": null
    },
    {
      "personId": 224,
      "characterName": "Reginald Hargreeves",
      "characterImage": null
    },
    {
      "personId": 980,
      "characterName": "Lila Pitts",
      "characterImage": null
    },
    {
      "personId": 612,
      "characterName": "Grace",
      "characterImage": null
    },
    {
      "personId": 647,
      "characterName": "The Handler",
      "characterImage": null
    },
    {
      "personId": 163,
      "characterName": "Hazel",
      "characterImage": null
    },
    {
      "personId": 797,
      "characterName": "Cha-Cha",
      "characterImage": null
    },
    {
      "personId": 1231,
      "characterName": "Pogo",
      "characterImage": "characters/the_umbrella_academy_pogo.webp"
    }
  ],
  "collections": [
    {
      "collectionId": 16,
      "order": null
    }
  ],
  "countries": [
    {
      "countryId": 1
    }
  ],
  "crew": [
    {
      "personId": 2265,
      "position": "CREATOR",
      "comment": null
    },
    {
      "personId": 2266,
      "position": "DIRECTOR",
      "comment": "2 episodes"
    },
    {
      "personId": 2267,
      "position": "DIRECTOR",
      "comment": "2 episodes"
    },
    {
      "personId": 2268,
      "position": "DIRECTOR",
      "comment": "4 episodes"
    },
    {
      "personId": 2269,
      "position": "DIRECTOR",
      "comment": "4 episodes"
    },
    {
      "personId": 1777,
      "position": "DIRECTOR",
      "comment": "4 episodes"
    },
    {
      "personId": 2270,
      "position": "DIRECTOR",
      "comment": "3 episodes"
    },
    {
      "personId": 2271,
      "position": "DIRECTOR",
      "comment": "2 episodes"
    },
    {
      "personId": 2272,
      "position": "DIRECTOR",
      "comment": "2 episodes"
    },
    {
      "personId": 2273,
      "position": "DIRECTOR",
      "comment": "2 episodes"
    },
    {
      "personId": 2274,
      "position": "DIRECTOR",
      "comment": "2 episodes"
    },
    {
      "personId": 2275,
      "position": "DIRECTOR",
      "comment": "1 episode"
    },
    {
      "personId": 2276,
      "position": "DIRECTOR",
      "comment": "2 episodes"
    },
    {
      "personId": 2265,
      "position": "WRITER",
      "comment": "1 episode"
    },
    {
      "personId": 2277,
      "position": "WRITER",
      "comment": "3 episodes"
    },
    {
      "personId": 2278,
      "position": "WRITER",
      "comment": "2 episodes"
    },
    {
      "personId": 2279,
      "position": "WRITER",
      "comment": "2 episodes"
    },
    {
      "personId": 2280,
      "position": "WRITER",
      "comment": "2 episodes"
    },
    {
      "personId": 2281,
      "position": "WRITER",
      "comment": "2 episodes"
    },
    {
      "personId": 2282,
      "position": "WRITER",
      "comment": "2 episodes"
    },
    {
      "personId": 2283,
      "position": "WRITER",
      "comment": "1 episode"
    },
    {
      "personId": 2284,
      "position": "WRITER",
      "comment": "2 episodes"
    },
    {
      "personId": 2285,
      "position": "WRITER",
      "comment": "4 episodes"
    },
    {
      "personId": 2286,
      "position": "WRITER",
      "comment": "2 episodes"
    },
    {
      "personId": 2287,
      "position": "WRITER",
      "comment": "5 episodes"
    },
    {
      "personId": 2288,
      "position": "WRITER",
      "comment": "3 episodes"
    },
    {
      "personId": 2289,
      "position": "WRITER",
      "comment": "1 episode"
    },
    {
      "personId": 2290,
      "position": "WRITER",
      "comment": "1 episode"
    },
    {
      "personId": 2291,
      "position": "WRITER",
      "comment": "1 episode"
    },
    {
      "personId": 2292,
      "position": "WRITER",
      "comment": "2 episodes"
    },
    {
      "personId": 1789,
      "position": "PRODUCER",
      "comment": null
    },
    {
      "personId": 2282,
      "position": "PRODUCER",
      "comment": null
    },
    {
      "personId": 2293,
      "position": "PRODUCER",
      "comment": null
    },
    {
      "personId": 2294,
      "position": "PRODUCER",
      "comment": null
    },
    {
      "personId": 2295,
      "position": "PRODUCER",
      "comment": null
    },
    {
      "personId": 2296,
      "position": "COMPOSER",
      "comment": null
    },
    {
      "personId": 2297,
      "position": "COMPOSER",
      "comment": null
    },
    {
      "personId": 2298,
      "position": "CAMERAMAN",
      "comment": null
    },
    {
      "personId": 2299,
      "position": "CAMERAMAN",
      "comment": null
    }
  ],
  "genres": [
    {
      "genreId": 2
    },
    {
      "genreId": 6
    }
  ],
  "studios": [
    {
      "studioId": 17
    }
  ],
  "seriesExtension": {
    "episodesTotal": 30,
    "seasonsTotal": 3,
    "seasons": [
      {
        "number": 1,
        "episodesCount": 10,
        "releaseDate": "2019-02-15T00:00:00.000Z"
      },
      {
        "number": 2,
        "episodesCount": 10,
        "releaseDate": "2020-07-31T00:00:00.000Z"
      },
      {
        "number": 3,
        "episodesCount": 10,
        "releaseDate": "2022-06-22T00:00:00.000Z"
      }
    ]
  },
  "trailers": [
    {
      "videoId": "0DAmWHxeoKw",
      "order": 1
    },
    {
      "videoId": "SGgXLbZnr1Y",
      "order": 2
    },
    {
      "videoId": "04Wns6ZHh6g",
      "order": 3
    }
  ]
}